dauber/__init__.py
dauber/inventory.py
dauber/playbook.py
dauber-0.0.0.post1.dist-info/DESCRIPTION.rst
dauber-0.0.0.post1.dist-info/METADATA
dauber-0.0.0.post1.dist-info/RECORD
dauber-0.0.0.post1.dist-info/WHEEL
dauber-0.0.0.post1.dist-info/metadata.json
dauber-0.0.0.post1.dist-info/top_level.txt
