Metadata-Version: 2.0
Name: dauber
Version: 0.0.0.post1
Summary: APACHE licensed project for running ansible playbooks
Home-page: http://www.kitware.com
Author: Kitware Inc
Author-email: chris.kotfila@kitware.com
License: Apache 2.0
Keywords: ansible
Platform: UNKNOWN
